pyhealthbox3/__init__.py
pyhealthbox3/healthbox3.py
pyhealthbox3/models.py
pyhealthbox3-0.0.22.dist-info/METADATA
pyhealthbox3-0.0.22.dist-info/WHEEL
pyhealthbox3-0.0.22.dist-info/licenses/LICENSE
pyhealthbox3-0.0.22.dist-info/RECORD
