Metadata-Version: 2.3
Name: pyhealthbox3
Version: 0.0.22
Summary: Renson Healthbox3 Package
Project-URL: Homepage, https://github.com/rmassch/pyhealthbox3
Project-URL: Bug Tracker, https://github.com/rmassch/pyhealthbox3/issues
Author-email: rmassch <1083135+rmassch@users.noreply.github.com>
Classifier: License :: OSI Approved :: MIT License
Classifier: Operating System :: OS Independent
Classifier: Programming Language :: Python :: 3
Requires-Python: >=3.7
Requires-Dist: aiohttp
